stairstep/__init__.py
stairstep/base.py
stairstep/statetypes.py
stairstep/statetypes_choices.py
stairstep/validations.py
stairstep-0.1.dist-info/METADATA
stairstep-0.1.dist-info/RECORD
stairstep-0.1.dist-info/WHEEL
stairstep-0.1.dist-info/top_level.txt
tests/__init__.py
tests/test_01singlestep.py
tests/test_02stateoutput.py
tests/test_03fieldValidation.py
tests/test_04choicestate.py
tests/test_stairstep.py
