Metadata-Version: 2.1
Name: stairstep
Version: 0.1
Summary: A Pythonic API for Amazon's States Language for defining AWS Step Functions
Home-page: https://github.com/adamgilman/stairstep
Author: Adam Gilman
Author-email: oss+stairstep@adamgilman.com
License: UNKNOWN
Platform: UNKNOWN
Classifier: Programming Language :: Python :: 3
Classifier: License :: OSI Approved :: MIT License
Classifier: Operating System :: OS Independent
